sphinxcontrib_cjkspacer-0.4.3-py3.8-nspkg.pth
sphinxcontrib/cjkspacer.py
sphinxcontrib_cjkspacer-0.4.3.dist-info/LICENSE
sphinxcontrib_cjkspacer-0.4.3.dist-info/METADATA
sphinxcontrib_cjkspacer-0.4.3.dist-info/WHEEL
sphinxcontrib_cjkspacer-0.4.3.dist-info/namespace_packages.txt
sphinxcontrib_cjkspacer-0.4.3.dist-info/top_level.txt
sphinxcontrib_cjkspacer-0.4.3.dist-info/RECORD
