Metadata-Version: 2.1
Name: sphinxcontrib-cjkspacer
Version: 0.4.3
Summary: Sphinx "cjkspacer" extension
Home-page: https://github.com/tatsushi-ikeda/sphinxcontrib-cjkspacer
Author: tatsushi-ikeda
Author-email: ikeda.tatsushi.37u@kyoto-u.jp
License: MIT
Download-URL: http://pypi.python.org/pypi/sphinxcontrib-cjkspacer
Platform: any
Classifier: Development Status :: 4 - Beta
Classifier: Environment :: Console
Classifier: Environment :: Web Environment
Classifier: Intended Audience :: Developers
Classifier: License :: OSI Approved :: MIT License
Classifier: Operating System :: OS Independent
Classifier: Programming Language :: Python
Classifier: Topic :: Documentation
Classifier: Topic :: Utilities
Classifier: Natural Language :: Japanese
License-File: LICENSE
Requires-Dist: sphinx
